mag4/__init__.py
mag4/datasets.py
mag4-0.0.214.dist-info/METADATA
mag4-0.0.214.dist-info/WHEEL
mag4-0.0.214.dist-info/top_level.txt
mag4-0.0.214.dist-info/RECORD
