Metadata-Version: 2.1
Name: mag4
Version: 0.0.214
Summary: A Geochemistry and Cosmochemistry Data and Tools Package
Author: Dominik
Project-URL: Homepage, https://github.com/pypa/sampleproject
Project-URL: Issues, https://github.com/pypa/sampleproject/issues
Classifier: Programming Language :: Python :: 3
Classifier: License :: OSI Approved :: MIT License
Classifier: Operating System :: OS Independent
Requires-Python: >=3.8
